{
  "schemaVersion": "0.1",
  "name": "invisibleexit",
  "displayName": "Invisible Exit",
  "description": "Faceless side-business system for employed professionals — 5 AI tools to validate, launch, and grow anonymous micro-SaaS recurring revenue without quitting your job.",
  "homepageUrl": "https://invisibleexit.com/mcp",
  "contactEmail": "hello@invisibleexit.com",
  "publisher": {
    "name": "Invisible Exit",
    "url": "https://invisibleexit.com"
  },
  "endpoints": {
    "streamableHttp": "https://invisibleexit.com/api/mcp"
  },
  "transports": [
    "streamable-http"
  ],
  "capabilities": {
    "tools": true,
    "prompts": false,
    "resources": false
  },
  "tools": [
    {
      "name": "search_side_business_guides",
      "summary": "Search side-business guides and micro-SaaS playbooks by topic."
    },
    {
      "name": "get_freedom_calculator",
      "summary": "Calculate your freedom number — the monthly recurring revenue needed to cover living expenses."
    },
    {
      "name": "validate_idea",
      "summary": "Validate a micro-SaaS idea against 500+ scored blueprints."
    }
  ]
}
